README.rst
setup.cfg
setup.py
django_optimized_image.egg-info/PKG-INFO
django_optimized_image.egg-info/SOURCES.txt
django_optimized_image.egg-info/dependency_links.txt
django_optimized_image.egg-info/requires.txt
django_optimized_image.egg-info/top_level.txt
optimized_image/__init__.py
optimized_image/admin.py
optimized_image/apps.py
optimized_image/fields.py
optimized_image/models.py
optimized_image/urls.py
optimized_image/utils.py
optimized_image/views.py
optimized_image/migrations/__init__.py
optimized_image/tests/__init__.py
optimized_image/tests/factories.py
optimized_image/tests/test_fields.py
optimized_image/tests/test_utils.py