Metadata-Version: 1.1
Name: django-optimized-image
Version: 0.1.0
Summary: A simple Django app that allows for optimization of images.
Home-page: https://github.com/dchukhin/django_optimized_image
Author: Dmitriy Chukhin
Author-email: dchukhin@caktusgroup.com
License: BSD License
Download-URL: https://github.com/dchukhin/django_optimized_image/tarball/0.1.0
Keywords: django,image,optimize,imagefield
Platform: UNKNOWN
Classifier: Environment :: Web Environment
Classifier: Framework :: Django
Classifier: Intended Audience :: Developers
Classifier: License :: OSI Approved :: BSD License
Classifier: Operating System :: OS Independent
Classifier: Programming Language :: Python
Classifier: Programming Language :: Python :: 3
Classifier: Programming Language :: Python :: 3.5
Classifier: Programming Language :: Python :: 3.6
Classifier: Topic :: Internet :: WWW/HTTP
Classifier: Topic :: Internet :: WWW/HTTP :: Dynamic Content
